jasyllablesep/__init__.py
jasyllablesep/core.py
jasyllablesep-0.0.0.dist-info/LICENSE
jasyllablesep-0.0.0.dist-info/METADATA
jasyllablesep-0.0.0.dist-info/WHEEL
jasyllablesep-0.0.0.dist-info/top_level.txt
jasyllablesep-0.0.0.dist-info/RECORD
